{
    "items": [
        {
            "stageId": 1,
            "stageTime": 60,
            "leafTime": 5,
            "leafNum": 20,
            "leafSpeed": 5,
            "leafPoint": 20,
            "obstacleIds":"1",
			"obstacleRates":"0",
            "obstacleTime": 7,
            "obstacleNum": 0,
            "supportIds": "1",
			"supportRates":"100",
            "supportTime": 7,
            "supportNum": 5
        },
        {
            "stageId": 2,
            "stageTime": 60,
            "leafTime": 5,
            "leafNum": 20,
            "leafSpeed": 5,
            "leafPoint": 20,
            "obstacleIds":"20,21",
			"obstacleRates":"10,10",
            "obstacleTime": 7,
            "obstacleNum": 1,
            "supportIds": "1,2",
			"supportRates":"50,50",
            "supportTime": 7,
            "supportNum": 2
        },
        {
            "stageId": 3,
            "stageTime": 60,
            "leafTime": 5,
            "leafNum": 20,
            "leafSpeed": 6,
            "leafPoint": 30,
            "obstacleIds":"1,10",
			"obstacleRates":"50,50",
            "obstacleTime": 5,
            "obstacleNum": 2,
            "supportIds": "1",
			"supportRates":"100",
            "supportTime": 7,
            "supportNum": 5
        },
        {
            "stageId": 4,
            "stageTime": 60,
            "leafTime": 5,
            "leafNum": 20,
            "leafSpeed": 6,
            "leafPoint": 30,
            "obstacleIds":"10,20,21,22,23",
			"obstacleRates":"20,20,20,20,20",
            "obstacleTime": 5,
            "obstacleNum": 3,
            "supportIds": "1,2,3",
			"supportRates":"50,30,20",
            "supportTime": 7,
            "supportNum": 5
        },
        {
            "stageId": 5,
            "stageTime": 60,
            "leafTime": 4,
            "leafNum": 20,
            "leafSpeed": 7,
            "leafPoint": 40,
            "obstacleIds":"10,20,21,22,23,24,25,26",
			"obstacleRates":"13,13,13,13,12,12,12,12",
            "obstacleTime": 4,
            "obstacleNum": 5,
            "supportIds": "1,4",
			"supportRates":"40,60",
            "supportTime": 6,
            "supportNum": 5        
		},
        {
            "stageId": 6,
            "stageTime": 60,
            "leafTime": 4,
            "leafNum": 20,
            "leafSpeed": 7,
            "leafPoint": 40,
            "obstacleIds":"20",
			"obstacleRates":"0",
            "obstacleTime": 1,
            "obstacleNum": 0,
            "supportIds": "4",
			"supportRates":"100",
            "supportTime": 6,
            "supportNum": 5
        },
        {
            "stageId": 7,
            "stageTime": 60,
            "leafTime": 4,
            "leafNum": 20,
            "leafSpeed": 8,
            "leafPoint": 50,
            "obstacleIds":"1,10,11,27,28,29",
			"obstacleRates":"20,16,16,16,16,16",
            "obstacleTime": 3,
            "obstacleNum": 5,
            "supportIds": "1,2,3,4",
			"supportRates":"20,20,20,20",
            "supportTime": 6,
            "supportNum": 5
        },
        {
            "stageId": 8,
            "stageTime": 60,
            "leafTime": 4,
            "leafNum": 20,
            "leafSpeed": 8,
            "leafPoint": 50,
            "obstacleIds":"27,28,29",
			"obstacleRates":"40,30,30",
            "obstacleTime": 1,
            "obstacleNum": 2,
            "supportIds": "1,2,3,4",
			"supportRates":"20,10,10,60",
            "supportTime": 6,
            "supportNum": 5
        },
        {
            "stageId": 9,
            "stageTime": 60,
            "leafTime": 4,
            "leafNum": 20,
            "leafSpeed": 9,
            "leafPoint": 60,
            "obstacleIds":"1,10,20,21,22,23",
			"obstacleRates":"30,15,15,15,15,10",
            "obstacleTime": 2,
            "obstacleNum": 5,
            "supportIds": "1,2,3,4",
			"supportRates":"20,20,20,20",
            "supportTime": 5,
            "supportNum": 5
        },
        {
            "stageId": 10,
            "stageTime": 60,
            "leafTime": 3,
            "leafNum": 20,
            "leafSpeed": 9,
            "leafPoint": 60,
            "obstacleIds":"25,26,27,28,29",
			"obstacleRates":"20,20,20,20",
            "obstacleTime": 1,
            "obstacleNum": 10,
            "supportIds": "1",
			"supportRates":"100",
            "supportTime": 2,
            "supportNum": 5
        },
        {
            "stageId": 11,
            "stageTime": 60,
            "leafTime": 3,
            "leafNum": 20,
            "leafSpeed": 10,
            "leafPoint": 60,
            "obstacleIds":"1",
			"obstacleRates":"100",
            "obstacleTime": 1,
            "obstacleNum": 4,
            "supportIds": "1,2,3,4",
			"supportRates":"20,20,20,20",
            "supportTime": 5,
            "supportNum": 4
        },
        {
            "stageId": 12,
            "stageTime": 60,
            "leafTime": 3,
            "leafNum": 20,
            "leafSpeed": 10,
            "leafPoint": 70,
            "obstacleIds":"1,10,11,20,21,22,23,27,28,29",
			"obstacleRates":"10,10,10,10,10,10,10,10,10,10",
            "obstacleTime": 1,
            "obstacleNum": 4,
            "supportIds": "1,2,3,4",
			"supportRates":"20,20,20,20",
            "supportTime": 5,
            "supportNum": 5
        }
    ]
}